SubsidiosConsolidados/Consolidados_Subsidios.py
SubsidiosConsolidados/__init__.py
subsidiosconsolidados-0.1.1.dist-info/METADATA
subsidiosconsolidados-0.1.1.dist-info/WHEEL
subsidiosconsolidados-0.1.1.dist-info/top_level.txt
subsidiosconsolidados-0.1.1.dist-info/RECORD
