Metadata-Version: 2.4
Name: SubsidiosConsolidados
Version: 0.1.1
Summary: A library to create a book of excel
Home-page: https://gitlab.com/fyamith.tovar
Author: Fabian Tovar
Author-email: fabianyamith123@gmail.com
License: MIT
Classifier: License :: OSI Approved :: MIT License
Classifier: Programming Language :: Python :: 3
Classifier: Operating System :: OS Independent
Dynamic: author
Dynamic: author-email
Dynamic: classifier
Dynamic: home-page
Dynamic: license
Dynamic: summary
